LICENSE
MANIFEST.in
README.rst
setup.cfg
setup.py
gapic_google_pubsub_v1.egg-info/PKG-INFO
gapic_google_pubsub_v1.egg-info/SOURCES.txt
gapic_google_pubsub_v1.egg-info/dependency_links.txt
gapic_google_pubsub_v1.egg-info/namespace_packages.txt
gapic_google_pubsub_v1.egg-info/requires.txt
gapic_google_pubsub_v1.egg-info/top_level.txt
google/__init__.py
google/__init__.pyc
google/cloud/__init__.py
google/cloud/__init__.pyc
google/cloud/gapic/__init__.py
google/cloud/gapic/pubsub/__init__.py
google/cloud/gapic/pubsub/v1/__init__.py
google/cloud/gapic/pubsub/v1/publisher_api.py
google/cloud/gapic/pubsub/v1/publisher_client_config.json
google/cloud/gapic/pubsub/v1/subscriber_api.py
google/cloud/gapic/pubsub/v1/subscriber_client_config.json