Metadata-Version: 1.1
Name: gapic-google-pubsub-v1
Version: 0.9.3
Summary: GAPIC library for the Google Pubsub API
Home-page: https://github.com/googleapis/googleapis
Author: Google Inc
Author-email: googleapis-packages@google.com
License: Apache-2.0
Platform: UNKNOWN
Classifier: Intended Audience :: Developers
Classifier: Development Status :: 3 - Alpha
Classifier: Intended Audience :: Developers
Classifier: License :: OSI Approved :: Apache Software License
Classifier: Programming Language :: Python
Classifier: Programming Language :: Python :: 2.7
Classifier: Programming Language :: Python :: Implementation :: CPython
